README.rst
setup.py
afthermal/__init__.py
afthermal/cli.py
afthermal/hw.py
afthermal/port.py
afthermal/text.py
afthermal/util.py
afthermal.egg-info/PKG-INFO
afthermal.egg-info/SOURCES.txt
afthermal.egg-info/dependency_links.txt
afthermal.egg-info/entry_points.txt
afthermal.egg-info/requires.txt
afthermal.egg-info/top_level.txt
afthermal/img/__init__.py
afthermal/img/floydsteinberg.c
afthermal/img/opencv.py
afthermal/img/pil.py
afthermal/img/qr.py