Metadata-Version: 1.0
Name: afthermal
Version: 0.3.1
Summary: UNKNOWN
Home-page: http://github.com/mbr/afthermal
Author: Marc Brinkmann
Author-email: git@marcbrinkmann.de
License: MIT
Platform: UNKNOWN
